setup.py
str2date/__init__.py
str2date/str2date.py
str2date.egg-info/PKG-INFO
str2date.egg-info/SOURCES.txt
str2date.egg-info/dependency_links.txt
str2date.egg-info/top_level.txt
test/test.py