Metadata-Version: 1.1
Name: str2date
Version: 0.905
Summary: Proper Parser of ISO 8601 Calendar Date and Time Strings
Home-page: https://github.com/avnr/str2date
Author: Avner Herskovits
Author-email: avnr_ at outlook.com
License: UNKNOWN
Download-URL: https://github.com/avnr/str2date/tarball/0.905
Platform: UNKNOWN
Classifier: Development Status :: 4 - Beta
Classifier: Environment :: Other Environment
Classifier: Intended Audience :: Developers
Classifier: License :: OSI Approved :: MIT License
Classifier: Operating System :: OS Independent
Classifier: Programming Language :: Python
Classifier: Topic :: Software Development :: Libraries
